X35SuiChengxuyuanDeTuiluLianghuaTouziXuexiBiji20210730/README.md
X35SuiChengxuyuanDeTuiluLianghuaTouziXuexiBiji20210730/__init__.py
X35SuiChengxuyuanDeTuiluLianghuaTouziXuexiBiji20210730/__main__.py
X35SuiChengxuyuanDeTuiluLianghuaTouziXuexiBiji20210730/file.epub
X35SuiChengxuyuanDeTuiluLianghuaTouziXuexiBiji20210730/index.html
X35SuiChengxuyuanDeTuiluLianghuaTouziXuexiBiji20210730/css/__init__.py
X35SuiChengxuyuanDeTuiluLianghuaTouziXuexiBiji20210730/css/annotations.css
X35SuiChengxuyuanDeTuiluLianghuaTouziXuexiBiji20210730/css/main.css
X35SuiChengxuyuanDeTuiluLianghuaTouziXuexiBiji20210730/css/normalize.css
X35SuiChengxuyuanDeTuiluLianghuaTouziXuexiBiji20210730/css/popup.css
X35SuiChengxuyuanDeTuiluLianghuaTouziXuexiBiji20210730/font/__init__.py
X35SuiChengxuyuanDeTuiluLianghuaTouziXuexiBiji20210730/font/fontello.eot
X35SuiChengxuyuanDeTuiluLianghuaTouziXuexiBiji20210730/font/fontello.svg
X35SuiChengxuyuanDeTuiluLianghuaTouziXuexiBiji20210730/font/fontello.ttf
X35SuiChengxuyuanDeTuiluLianghuaTouziXuexiBiji20210730/font/fontello.woff
X35SuiChengxuyuanDeTuiluLianghuaTouziXuexiBiji20210730/img/__init__.py
X35SuiChengxuyuanDeTuiluLianghuaTouziXuexiBiji20210730/img/annotator-glyph-sprite.png
X35SuiChengxuyuanDeTuiluLianghuaTouziXuexiBiji20210730/img/annotator-icon-sprite.png
X35SuiChengxuyuanDeTuiluLianghuaTouziXuexiBiji20210730/img/apple-touch-icon.png
X35SuiChengxuyuanDeTuiluLianghuaTouziXuexiBiji20210730/img/cancelfullscreen.png
X35SuiChengxuyuanDeTuiluLianghuaTouziXuexiBiji20210730/img/close.png
X35SuiChengxuyuanDeTuiluLianghuaTouziXuexiBiji20210730/img/fullscreen.png
X35SuiChengxuyuanDeTuiluLianghuaTouziXuexiBiji20210730/img/loader.gif
X35SuiChengxuyuanDeTuiluLianghuaTouziXuexiBiji20210730/img/menu-icon.png
X35SuiChengxuyuanDeTuiluLianghuaTouziXuexiBiji20210730/img/save.png
X35SuiChengxuyuanDeTuiluLianghuaTouziXuexiBiji20210730/img/saved.png
X35SuiChengxuyuanDeTuiluLianghuaTouziXuexiBiji20210730/img/settings-s.png
x35_sui_chengxuyuan_de_tuilu_lianghua_touzi_xuexi_biji_20210730-2024.3.6.0.dist-info/METADATA
x35_sui_chengxuyuan_de_tuilu_lianghua_touzi_xuexi_biji_20210730-2024.3.6.0.dist-info/WHEEL
x35_sui_chengxuyuan_de_tuilu_lianghua_touzi_xuexi_biji_20210730-2024.3.6.0.dist-info/entry_points.txt
x35_sui_chengxuyuan_de_tuilu_lianghua_touzi_xuexi_biji_20210730-2024.3.6.0.dist-info/top_level.txt
x35_sui_chengxuyuan_de_tuilu_lianghua_touzi_xuexi_biji_20210730-2024.3.6.0.dist-info/RECORD
